mcp_elevenlabs/__init__.py
mcp_elevenlabs/server.py
mcp_elevenlabs-0.0.2.dist-info/METADATA
mcp_elevenlabs-0.0.2.dist-info/WHEEL
mcp_elevenlabs-0.0.2.dist-info/entry_points.txt
mcp_elevenlabs-0.0.2.dist-info/top_level.txt
mcp_elevenlabs-0.0.2.dist-info/RECORD
