Metadata-Version: 2.4
Name: mcp-elevenlabs
Version: 0.0.2
Summary: MCP server for Elevenlabs integration
Project-URL: Homepage, https://github.com/your-username/mcp-elevenlabs
Project-URL: Bug Tracker, https://github.com/your-username/mcp-elevenlabs/issues
Requires-Python: >=3.10
Requires-Dist: mcp[cli]>=1.6.0
Requires-Dist: httpx>=0.24.0
